{
  "type": "Feature",
  "properties": {
    "iso:country":"IL",
    "sg:address":"Yakum Business Park",
    "sg:city":"Yakum",
    "sg:classifiers":[
        {
            "category":"Professional",
            "subcategory":"Computer Services",
            "type":"Services"
        }
    ],
    "sg:postcode":"60972",
    "sg:website":"http://www.mtlk.com/",
    "wof:name":"MetaLink",
    "wof:placetype":"venue"
},
  "geometry": {"coordinates":[-95.712891,37.09024],"type":"Point"}
}